{
  "name": "Person",
  "fields": [
    {
      "fieldName": "name",
      "fieldType": "String"
    },
    {
      "fieldName": "birth",
      "fieldType": "Instant"
    },
    {
      "fieldName": "status",
      "fieldType": "String"
    },
    {
      "fieldName": "country",
      "fieldType": "String"
    },
    {
      "fieldName": "city",
      "fieldType": "String"
    }
  ],
  "relationships": [],
  "changelogDate": "20220224103445",
  "entityTableName": "person",
  "dto": "mapstruct",
  "pagination": "no",
  "service": "serviceImpl",
  "jpaMetamodelFiltering": false,
  "fluentMethods": true,
  "readOnly": false,
  "embedded": false,
  "clientRootFolder": "",
  "applications": "*"
}
